tlhelp32/__init__.py
tlhelp32/__main__.py
tlhelp32/_base.py
tlhelp32/_ctypes.py
tlhelp32/errors.py
tlhelp32/heap.py
tlhelp32/module.py
tlhelp32/process.py
tlhelp32/snapshot.py
tlhelp32/thread.py
tlhelp32-0.1.0.dist-info/LICENSE
tlhelp32-0.1.0.dist-info/METADATA
tlhelp32-0.1.0.dist-info/WHEEL
tlhelp32-0.1.0.dist-info/entry_points.txt
tlhelp32-0.1.0.dist-info/top_level.txt
tlhelp32-0.1.0.dist-info/RECORD
