Metadata-Version: 2.1
Name: tlhelp32
Version: 0.1.0
Summary: An idiomatic Python API for the Windows Tool Help library
Home-page: https://github.com/demberto/tlhelp32
Author: demberto
Author-email: demberto@protonmail.com
License: ISC
Project-URL: Homepage, https://github.com/demberto/tlhelp32
Project-URL: Documentation, https://tlhelp32.rtfd.io/
Project-URL: Source, https://github.com/demberto/tlhelp32
Project-URL: Tracker, https://github.com/demberto/tlhelp32/issues
Project-URL: Changelog, https://github.com/demberto/tlhelp32/blob/master/CHANGELOG.md
Keywords: windows,tool-help,debug,win32
Platform: windows
Classifier: Development Status :: 3 - Alpha
Classifier: Intended Audience :: Developers
Classifier: License :: OSI Approved :: ISC License (ISCL)
Classifier: Natural Language :: English
Classifier: Operating System :: Microsoft :: Windows
Classifier: Programming Language :: Python :: 3
Classifier: Programming Language :: Python :: 3 :: Only
Classifier: Programming Language :: Python :: 3.7
Classifier: Programming Language :: Python :: 3.8
Classifier: Programming Language :: Python :: 3.9
Classifier: Programming Language :: Python :: 3.10
Classifier: Topic :: Software Development :: Libraries
Requires-Python: >=3.7
License-File: LICENSE
Requires-Dist: typing-extensions
